sublime_from_cfg/__init__.py
sublime_from_cfg/bnf.py
sublime_from_cfg/cli.py
sublime_from_cfg/parse_sbnf.py
sublime_from_cfg/sublime_generator.py
sublime_from_cfg/transform_grammar.py
sublime_from_cfg/types.py
sublime_from_cfg-0.2.0.dist-info/LICENSE
sublime_from_cfg-0.2.0.dist-info/METADATA
sublime_from_cfg-0.2.0.dist-info/WHEEL
sublime_from_cfg-0.2.0.dist-info/entry_points.txt
sublime_from_cfg-0.2.0.dist-info/top_level.txt
sublime_from_cfg-0.2.0.dist-info/RECORD
