Metadata-Version: 2.1
Name: sublime-from-cfg
Version: 0.2.0
Summary: Generate a Sublime Text syntax definition for a context-free grammar
Home-page: https://github.com/nuchi/sublime-from-cfg
Author: Haggai Nuchi
Author-email: haggai@haggainuchi.com
License: MIT
Keywords: sublime text,context-free grammar,sbnf,bnf
Platform: any
License-File: LICENSE
Requires-Dist: sly (>=0.4)
Requires-Dist: ruamel.yaml (>=0.17.17)
